mahotas/mahotas_version.py
mahotas/morph.py
mahotas/_convolve.cpython-36m-x86_64-linux-gnu.so
mahotas/histogram.py
mahotas/_labeled.cpython-36m-x86_64-linux-gnu.so
mahotas/segmentation.py
mahotas/resize.py
mahotas/interpolate.py
mahotas/_convex.cpython-36m-x86_64-linux-gnu.so
mahotas/thresholding.py
mahotas/euler.py
mahotas/convolve.py
mahotas/internal.py
mahotas/_distance.cpython-36m-x86_64-linux-gnu.so
mahotas/bwperim.py
mahotas/_filters.py
mahotas/_bbox.cpython-36m-x86_64-linux-gnu.so
mahotas/polygon.py
mahotas/lbp.py
mahotas/__init__.py
mahotas/center_of_mass.py
mahotas/_thin.cpython-36m-x86_64-linux-gnu.so
mahotas/_morph.cpython-36m-x86_64-linux-gnu.so
mahotas/colors.py
mahotas/stretch.py
mahotas/surf.py
mahotas/_center_of_mass.cpython-36m-x86_64-linux-gnu.so
mahotas/_interpolate.cpython-36m-x86_64-linux-gnu.so
mahotas/texture.py
mahotas/_histogram.cpython-36m-x86_64-linux-gnu.so
mahotas/labeled.py
mahotas/tas.py
mahotas/moments.py
mahotas/distance.py
mahotas/thin.py
mahotas/zernike.py
mahotas/freeimage.py
mahotas/features_cli.py
mahotas/edge.py
mahotas/bbox.py
mahotas/features/_surf.cpython-36m-x86_64-linux-gnu.so
mahotas/features/_lbp.cpython-36m-x86_64-linux-gnu.so
mahotas/features/_zernike.cpython-36m-x86_64-linux-gnu.so
mahotas/features/lbp.py
mahotas/features/__init__.py
mahotas/features/surf.py
mahotas/features/texture.py
mahotas/features/tas.py
mahotas/features/moments.py
mahotas/features/_texture.cpython-36m-x86_64-linux-gnu.so
mahotas/features/shape.py
mahotas/features/zernike.py
mahotas/demos/wally.py
mahotas/demos/nuclear.py
mahotas/demos/thresholding.py
mahotas/demos/surf_luispedro.py
mahotas/demos/edge_demo.py
mahotas/demos/superpixels.py
mahotas/demos/nuclear_distance_watershed.py
mahotas/demos/__init__.py
mahotas/demos/wavelet_compress.py
mahotas/demos/surf_gaussians.py
mahotas/demos/morphology.py
mahotas/demos/distance.py
mahotas/demos/data/lena.jpg
mahotas_nh-1.4.10.dist-info/RECORD
mahotas_nh-1.4.10.dist-info/WHEEL
mahotas_nh-1.4.10.dist-info/top_level.txt
mahotas_nh-1.4.10.dist-info/COPYING
mahotas_nh-1.4.10.dist-info/METADATA
mahotas_nh-1.4.10.dist-info/AUTHORS
mahotas_nh-1.4.10.dist-info/entry_points.txt
